quaerere_base_flask/__init__.py
quaerere_base_flask/schemas/__init__.py
quaerere_base_flask/views/__init__.py
quaerere_base_flask/views/base.py
quaerere_base_flask-0.3.0.dist-info/LICENSE.txt
quaerere_base_flask-0.3.0.dist-info/METADATA
quaerere_base_flask-0.3.0.dist-info/WHEEL
quaerere_base_flask-0.3.0.dist-info/dependency_links.txt
quaerere_base_flask-0.3.0.dist-info/entry_points.txt
quaerere_base_flask-0.3.0.dist-info/top_level.txt
quaerere_base_flask-0.3.0.dist-info/RECORD
