Metadata-Version: 2.1
Name: quaerere-base-flask
Version: 0.3.0
Summary: Base for QuaererePlatform projects that utilize Flask
Home-page: https://github.com/QuaererePlatform/quaerere-base-flask
Author: Caitlyn O'Hanna
Author-email: ravenoak@virtualxistenz.com
License: AGPLv3+
Project-URL: Documentation, http://quaerere-base-flask.readthedocs.io/
Project-URL: Source Code, https://github.com/QuaererePlatform/quaerere-base-flask
Platform: UNKNOWN
Classifier: Development Status :: 2 - Pre-Alpha
Classifier: Environment :: Web Environment
Classifier: Framework :: Flask
Classifier: License :: OSI Approved :: GNU Affero General Public License v3 or later (AGPLv3+)
Classifier: Operating System :: OS Independent
Classifier: Programming Language :: Python :: 3 :: Only
Classifier: Programming Language :: Python :: 3.7
Requires-Python: >= 3.6
Requires-Dist: Flask-Classful (>=0.14.2)
Requires-Dist: arango-orm (==0.5.7)
Requires-Dist: python-arango (<5,>=4.4.0)
Requires-Dist: marshmallow (<3,>=2.16.0)
